odoo/addons/l10n_it_fatturapa_out_di/README.rst
odoo/addons/l10n_it_fatturapa_out_di/__init__.py
odoo/addons/l10n_it_fatturapa_out_di/__manifest__.py
odoo/addons/l10n_it_fatturapa_out_di/data/invoice_it_template.xml
odoo/addons/l10n_it_fatturapa_out_di/i18n/it.po
odoo/addons/l10n_it_fatturapa_out_di/i18n/l10n_it_fatturapa_out_di.pot
odoo/addons/l10n_it_fatturapa_out_di/i18n/l10n_it_fatturapa_out_sp.pot
odoo/addons/l10n_it_fatturapa_out_di/readme/CONTRIBUTORS.rst
odoo/addons/l10n_it_fatturapa_out_di/readme/DESCRIPTION.rst
odoo/addons/l10n_it_fatturapa_out_di/static/description/icon.png
odoo/addons/l10n_it_fatturapa_out_di/static/description/index.html
odoo/addons/l10n_it_fatturapa_out_di/tests/__init__.py
odoo/addons/l10n_it_fatturapa_out_di/tests/fatturapa_common.py
odoo/addons/l10n_it_fatturapa_out_di/tests/test_fatturapa_xml_validation.py
odoo/addons/l10n_it_fatturapa_out_di/tests/data/IT06363391001_00001.xml
odoo/addons/l10n_it_fatturapa_out_di/tests/data/IT06363391001_00002.xml
odoo/addons/l10n_it_fatturapa_out_di/tests/data/IT06363391001_00003.xml
odoo14_addon_l10n_it_fatturapa_out_di-14.0.1.0.5.dist-info/METADATA
odoo14_addon_l10n_it_fatturapa_out_di-14.0.1.0.5.dist-info/WHEEL
odoo14_addon_l10n_it_fatturapa_out_di-14.0.1.0.5.dist-info/top_level.txt
odoo14_addon_l10n_it_fatturapa_out_di-14.0.1.0.5.dist-info/RECORD
